pywebcanvas/__init__.py
pywebcanvas/background.py
pywebcanvas/canvas.py
pywebcanvas/listener.py
pywebcanvas/logger.py
pywebcanvas/loop.py
pywebcanvas/rect.py
pywebcanvas/text.py
pywebcanvas-0.3.0.dist-info/entry_points.txt
pywebcanvas-0.3.0.dist-info/LICENSE.md
pywebcanvas-0.3.0.dist-info/WHEEL
pywebcanvas-0.3.0.dist-info/METADATA
pywebcanvas-0.3.0.dist-info/RECORD
