Metadata-Version: 2.1
Name: pywebcanvas
Version: 0.3.0
Summary: A library that allows users to interact with the HTML Canvas with 100% Python + HTML.
Home-page: https://gitlab.com/imbev/pywebcanvas
License: LGPL-3.0-or-later
Keywords: pyscript,web,canvas
Author: Isaac Beverly
Requires-Python: >=3.8,<4.0
Classifier: License :: OSI Approved :: GNU Lesser General Public License v3 or later (LGPLv3+)
Classifier: Programming Language :: Python :: 3
Classifier: Programming Language :: Python :: 3.10
Classifier: Programming Language :: Python :: 3.8
Classifier: Programming Language :: Python :: 3.9
Requires-Dist: colour (>=0.1.5,<0.2.0)
Requires-Dist: typer (>=0.4.1,<0.5.0)
Project-URL: Repository, https://gitlab.com/imbev/pywebcanvas.git
